comet/__init__.py
comet/bids.py
comet/cifti.py
comet/connectivity.py
comet/graph.py
comet/gui.py
comet/multiverse.py
comet/utils.py
comet/data/hurricane.tsv
comet/data/simulation.mat
comet/data/time_series.txt
comet/data/atlas/Q1-Q6_RelatedValidation210.CorticalAreas_dil_Final_Final_Areas_Group_Colors_with_Atlas_ROIs2.32k_fs_LR.dlabel.nii
comet/data/atlas/fs_LR_32k_medial_mask.mat
comet/data/img/content.drawio
comet/data/img/content.png
comet/data/img/doi.svg
comet/data/img/gui.png
comet/data/img/logo.png
comet/data/img/logo.svg
comet/data/img/pypi.svg
comet/data/tests/connectivity.mat
comet/data/tests/graph.mat
comet_toolbox-1.1.0.dist-info/METADATA
comet_toolbox-1.1.0.dist-info/WHEEL
comet_toolbox-1.1.0.dist-info/entry_points.txt
comet_toolbox-1.1.0.dist-info/licenses/LICENSE
comet_toolbox-1.1.0.dist-info/RECORD
