Metadata-Version: 2.4
Name: comet-toolbox
Version: 1.1.0
Summary: Dynamic functional connectivity toolbox for multiverse analysis
Project-URL: Homepage, https://github.com/mibur1/comet
Project-URL: Issues, https://github.com/mibur1/comet/issues
Author-email: Micha Burkhardt <micha.burkhardt@uol.de>
License: Copyright 2024 Micha Burkhardt
License-File: LICENSE
Classifier: License :: OSI Approved :: MIT License
Classifier: Operating System :: OS Independent
Classifier: Programming Language :: Python :: 3
Requires-Python: <3.14,>=3.11
Requires-Dist: bctpy>=0.6.1
Requires-Dist: hmmlearn>=0.3.3
Requires-Dist: importlib-resources>=6.5.2
Requires-Dist: ipykernel>=7.1.0
Requires-Dist: ipywidgets>=8.1.8
Requires-Dist: jinja2>=3.1.6
Requires-Dist: joblib>=1.5.2
Requires-Dist: ksvd>=0.0.3
Requires-Dist: mat73>=0.65
Requires-Dist: matplotlib>=3.10.7
Requires-Dist: networkx>=3.5
Requires-Dist: nibabel>=5.3.2
Requires-Dist: nilearn>=0.12.1
Requires-Dist: notebook>=7.4.7
Requires-Dist: numba>=0.62.1
Requires-Dist: numpy>=2.3.4
Requires-Dist: pandas>=2.3.3
Requires-Dist: pybids>=0.21.0
Requires-Dist: pycwt>=0.5.0b0
Requires-Dist: scikit-learn>=1.7.2
Requires-Dist: scipy>=1.16.3
Requires-Dist: seaborn>=0.13.2
Requires-Dist: statsmodels>=0.14.5
Requires-Dist: tqdm-joblib>=0.0.5
Requires-Dist: tqdm>=4.67.1
Provides-Extra: build
Requires-Dist: build>=1.3.0; extra == 'build'
Requires-Dist: hatchling>=1.27.0; extra == 'build'
Requires-Dist: twine>=6.2.0; extra == 'build'
Provides-Extra: doc
Requires-Dist: nbsphinx==0.9.6; extra == 'doc'
Requires-Dist: sphinx-autodoc-typehints>=1.14.0; extra == 'doc'
Requires-Dist: sphinx-rtd-theme>=3.0.2; extra == 'doc'
Requires-Dist: sphinx==8.1.3; extra == 'doc'
Provides-Extra: gui
Requires-Dist: pyqt6>=6.10.0; extra == 'gui'
Requires-Dist: qdarkstyle>=3.2.3; extra == 'gui'
Provides-Extra: test
Requires-Dist: pydfc>=1.0.7; extra == 'test'
Requires-Dist: pytest>=9.0.0; extra == 'test'
Requires-Dist: teneto>=0.5.3; extra == 'test'
